Metadata-Version: 2.1
Name: lfsdb
Version: 0.1.0.4
Summary: Local File Storage Database
Home-page: https://github.com/wxnacy/lfsdb
Author: wxnacy
Author-email: wxnacy@gmail.com
License: MIT
Platform: UNKNOWN
Classifier: License :: OSI Approved :: MIT License
Classifier: Programming Language :: Python
Classifier: Programming Language :: Python :: 3
Classifier: Programming Language :: Python :: 3.6
Classifier: Programming Language :: Python :: 3.7
Classifier: Programming Language :: Python :: Implementation :: CPython
Classifier: Programming Language :: Python :: Implementation :: PyPy
Requires-Python: >=3.6.0
License-File: LICENSE
